pyasyncialarm/__init__.py
pyasyncialarm/const.py
pyasyncialarm/exception.py
pyasyncialarm/pyasyncialarm.py
pyasyncialarm/util.py
pyasyncialarm-2.3.17.dist-info/LICENSE
pyasyncialarm-2.3.17.dist-info/METADATA
pyasyncialarm-2.3.17.dist-info/WHEEL
pyasyncialarm-2.3.17.dist-info/top_level.txt
pyasyncialarm-2.3.17.dist-info/RECORD
