Metadata-Version: 2.1
Name: pyasyncialarm
Version: 2.3.17
Summary: A simple library to interface with iAlarm systems, built for use with Home-Assistant
Author-email: Ludovico de Nittis <aasonykk+pyasyncialarm@gmail.com>
License: MIT OR Apache-2.0
Project-URL: Homepage, https://github.com/bigmoby/pyasyncialarm
Project-URL: Source Code, https://github.com/bigmoby/pyasyncialarm
Project-URL: Bug Reports, https://github.com/bigmoby/pyasyncialarm/issues
Keywords: ialarm,antifurtocasa365,alarm
Platform: any
Classifier: Development Status :: 4 - Beta
Classifier: Intended Audience :: Developers
Classifier: Programming Language :: Python :: 3.11
Classifier: License :: OSI Approved :: MIT License
Classifier: License :: OSI Approved :: Apache Software License
Classifier: Topic :: Software Development :: Libraries
Requires-Python: >=3.11.0
License-File: LICENSE
Requires-Dist: dicttoxml2
Requires-Dist: xmltodict
